defaultPDK/__init__.py
defaultPDK/callbacks.py
defaultPDK/compileNuitka.sh
defaultPDK/layoutLayers.py
defaultPDK/pcells.py
defaultPDK/process.py
defaultPDK/schLayers.py
defaultPDK/stipples/stipple1.txt
defaultPDK/stipples/stipple2.txt
defaultPDK/stipples/stipple3.txt
defaultPDK/stipples/stipple4.txt
defaultPDK/stipples/stipple5.txt
defaultPDK/stipples/stipple6.txt
defaultPDK/stipples/stipple7.txt
defaultPDK/symLayers.py
reveda.py
revedaEditor/__init__.py
revedaEditor/backend/__init__.py
revedaEditor/backend/claudeAiAgent.py
revedaEditor/backend/dataDefinitions.py
revedaEditor/backend/drcModelView.py
revedaEditor/backend/editFunctions.py
revedaEditor/backend/geminiAiAgent.py
revedaEditor/backend/hdlBackEnd.py
revedaEditor/backend/libBackEnd.py
revedaEditor/backend/libraryMethods.py
revedaEditor/backend/libraryModelView.py
revedaEditor/backend/pdkPaths.py
revedaEditor/backend/processManager.py
revedaEditor/backend/startThread.py
revedaEditor/backend/undoStack.py
revedaEditor/checks/__init__.py
revedaEditor/checks/schematic.py
revedaEditor/common/__init__.py
revedaEditor/common/labels.py
revedaEditor/common/layoutShapes.py
revedaEditor/common/net.py
revedaEditor/common/shapes.py
revedaEditor/fileio/__init__.py
revedaEditor/fileio/createSymbols.py
revedaEditor/fileio/exportGDS.py
revedaEditor/fileio/importGDS.py
revedaEditor/fileio/importLayp.py
revedaEditor/fileio/importSpice.py
revedaEditor/fileio/importVeriloga.py
revedaEditor/fileio/importXschemSym.py
revedaEditor/fileio/importlyrdb.py
revedaEditor/fileio/layoutEncoder.py
revedaEditor/fileio/loadJSON.py
revedaEditor/fileio/schematicEncoder.py
revedaEditor/fileio/symbolEncoder.py
revedaEditor/gui/__init__.py
revedaEditor/gui/aiTerminal.py
revedaEditor/gui/configEditor.py
revedaEditor/gui/editFunctions.py
revedaEditor/gui/editorViews.py
revedaEditor/gui/editorWindow.py
revedaEditor/gui/fileDialogues.py
revedaEditor/gui/helpBrowser.py
revedaEditor/gui/layoutDialogues.py
revedaEditor/gui/layoutEditor.py
revolution_eda-0.8.7.dist-info/METADATA
revolution_eda-0.8.7.dist-info/WHEEL
revolution_eda-0.8.7.dist-info/entry_points.txt
revolution_eda-0.8.7.dist-info/licenses/LICENSE.txt
revolution_eda-0.8.7.dist-info/RECORD
