Metadata-Version: 2.4
Name: revolution-eda
Version: 0.8.7
Summary: Custom IC Design Environment for Professionals
License: Mozilla Public License v2 modified by Commons Clause
License-File: LICENSE.txt
Keywords: EDA,IC Design,Semiconductor,Layout,Schematic
Author: Revolution Semiconductor
Author-email: 48187772+eskiyerli@users.noreply.github.com
Requires-Python: >=3.12,<3.14
Classifier: Intended Audience :: Science/Research
Classifier: License :: Other/Proprietary License
Classifier: Operating System :: OS Independent
Classifier: Programming Language :: Python :: 3
Classifier: Programming Language :: Python :: 3.12
Classifier: Programming Language :: Python :: 3.13
Classifier: Topic :: Scientific/Engineering :: Electronic Design Automation (EDA)
Requires-Dist: PySide6 (>=6.10.0)
Requires-Dist: anthropic (>=0.75.0,<0.76.0)
Requires-Dist: cryptography (>=46.0.3,<47.0.0)
Requires-Dist: gdstk (>=0.9.60,<0.10.0)
Requires-Dist: google-generativeai (>=0.8.5,<0.9.0)
Requires-Dist: lxml (>=6.0.0,<7.0.0)
Requires-Dist: markdown (>=3.9,<4.0)
Requires-Dist: numpy (>=2.3.1,<2.4.0)
Requires-Dist: orjson (>=3.11.4,<4.0.0)
Requires-Dist: polars (>=1.35.0,<1.36.0)
Requires-Dist: python-dotenv (>=1.2.0,<1.3.0)
Requires-Dist: quantiphy (>=2.20,<2.21)
Project-URL: Documentation, https://github.com/eskiyerli/revolution-eda/tree/master/docs
Project-URL: Homepage, https://github.com/eskiyerli/revolution-eda
Project-URL: Repository, https://github.com/eskiyerli/revolution-eda
